bitcoin_coin_selection/__init__.py
bitcoin_coin_selection/selection_algorithms/__init__.py
bitcoin_coin_selection/selection_algorithms/branch_and_bound.py
bitcoin_coin_selection/selection_algorithms/knapsack_solver.py
bitcoin_coin_selection/selection_algorithms/select_coins.py
bitcoin_coin_selection/selection_algorithms/single_random_draw.py
bitcoin_coin_selection/selection_types/__init__.py
bitcoin_coin_selection/selection_types/change_constants.py
bitcoin_coin_selection/selection_types/coin_selection.py
bitcoin_coin_selection/selection_types/coin_selection_params.py
bitcoin_coin_selection/selection_types/input_coin.py
bitcoin_coin_selection/selection_types/output_group.py
bitcoin_coin_selection/tests/__init__.py
bitcoin_coin_selection/tests/coin_selection_params.py
bitcoin_coin_selection/tests/fixtures.py
bitcoin_coin_selection/tests/test_branch_and_bound.py
bitcoin_coin_selection/tests/test_coin_selection.py
bitcoin_coin_selection/tests/test_knapsack_solver.py
bitcoin_coin_selection/tests/test_single_random_draw.py
selection_algorithms/__init__.py
selection_algorithms/branch_and_bound.py
selection_algorithms/knapsack_solver.py
selection_algorithms/select_coins.py
selection_algorithms/single_random_draw.py
selection_types/__init__.py
selection_types/change_constants.py
selection_types/coin_selection.py
selection_types/input_coin.py
selection_types/output_group.py
tests/__init__.py
tests/fixtures.py
tests/test_branch_and_bound.py
tests/test_coin_selection.py
tests/test_knapsack_solver.py
tests/test_single_random_draw.py
bitcoin_coin_selection-1.5.0.dist-info/LICENSE
bitcoin_coin_selection-1.5.0.dist-info/METADATA
bitcoin_coin_selection-1.5.0.dist-info/WHEEL
bitcoin_coin_selection-1.5.0.dist-info/top_level.txt
bitcoin_coin_selection-1.5.0.dist-info/RECORD
