Metadata-Version: 2.1
Name: bitcoin-coin-selection
Version: 1.5.0
Summary: Port of Bitcoin core coin selection logic to Python
Home-page: https://github.com/Kevingislason/bitcoin_coin_selection
Author: Kevin Gislason
Author-email: kevingislason@gmail.com
License: UNKNOWN
Platform: UNKNOWN
Classifier: Programming Language :: Python :: 3
Classifier: License :: OSI Approved :: MIT License
Classifier: Operating System :: OS Independent
Classifier: Topic :: Software Development :: Libraries
Requires-Python: >=3.6
